{
	"name": "Doom Armor",
	"icon": "doomweapon:doom_helmet",
	"category": "doomweapon:armor_category",
	"secret": false,
	"read_by_default": true,
	"pages": [
		{
			"type": "entity",
			"name": "Doom Armor",
			"entity": "minecraft:armor_stand{Invisible:1, ArmorItems:[{id:'doomweapon:doom_boots',Count:1},{id:'doomweapon:doom_leggings',Count:1},{id:'doomweapon:doom_chestplate',Count:1},{id:'doomweapon:doom_helmet',Count:1}]}",
			"rotate": true,
			"text": "The Armor fitting only for the slayer."
		},
		{
			"type": "crafting",
			"recipe": "doomweapon:doom_helmet",
			"recipe2": "doomweapon:doom_chestplate"
		},
		{
			"type": "crafting",
			"recipe": "doomweapon:doom_leggings",
			"recipe2": "doomweapon:doom_boots"
		}
	]
}
